{"cameraMode":{"drawMode":0,"name":"Shaded","section":"Shading Mode"},"sceneLighting":true,"audioPlay":false,"sceneViewState":{"m_AlwaysRefresh":false,"showFog":true,"showSkybox":true,"showFlares":true,"showImageEffects":true,"showParticleSystems":true,"showVisualEffectGraphs":true,"m_FxEnabled":true},"in2DMode":false,"pivot":{"x":-6.352847099304199,"y":-1.328155517578125,"z":-6.4250807762146},"rotation":{"x":-0.1882605105638504,"y":0.7658653259277344,"z":-0.258452445268631,"w":-0.55766361951828},"size":12.12435531616211,"orthographic":false}